clearvoice/__init__.py
clearvoice/network_wrapper.py
clearvoice/networks.py
clearvoice/config/inference/AV_MossFormer2_TSE_16K.yaml
clearvoice/config/inference/FRCRN_SE_16K.yaml
clearvoice/config/inference/MossFormer2_SE_48K.yaml
clearvoice/config/inference/MossFormer2_SR_48K.json
clearvoice/config/inference/MossFormer2_SR_48K.yaml
clearvoice/config/inference/MossFormer2_SS_16K.yaml
clearvoice/config/inference/MossFormerGAN_SE_16K.yaml
clearvoice/dataloader/__init__.py
clearvoice/dataloader/dataloader.py
clearvoice/dataloader/meldataset.py
clearvoice/dataloader/misc.py
clearvoice/models/__init__.py
clearvoice/models/av_mossformer2_tse/__init__.py
clearvoice/models/av_mossformer2_tse/av_mossformer2.py
clearvoice/models/av_mossformer2_tse/visual_frontend.py
clearvoice/models/av_mossformer2_tse/faceDetector/__init__.py
clearvoice/models/av_mossformer2_tse/faceDetector/s3fd/__init__.py
clearvoice/models/av_mossformer2_tse/faceDetector/s3fd/box_utils.py
clearvoice/models/av_mossformer2_tse/faceDetector/s3fd/nets.py
clearvoice/models/av_mossformer2_tse/mossformer/__init__.py
clearvoice/models/av_mossformer2_tse/mossformer/utils/Transformer.py
clearvoice/models/av_mossformer2_tse/mossformer/utils/__init__.py
clearvoice/models/av_mossformer2_tse/mossformer/utils/conv_module.py
clearvoice/models/av_mossformer2_tse/mossformer/utils/fsmn.py
clearvoice/models/av_mossformer2_tse/mossformer/utils/normalization.py
clearvoice/models/av_mossformer2_tse/mossformer/utils/one_path_flash_fsmn.py
clearvoice/models/frcrn_se/__init__.py
clearvoice/models/frcrn_se/complex_nn.py
clearvoice/models/frcrn_se/conv_stft.py
clearvoice/models/frcrn_se/frcrn.py
clearvoice/models/frcrn_se/se_layer.py
clearvoice/models/frcrn_se/unet.py
clearvoice/models/mossformer2_se/__init__.py
clearvoice/models/mossformer2_se/conv_module.py
clearvoice/models/mossformer2_se/fsmn.py
clearvoice/models/mossformer2_se/layer_norm.py
clearvoice/models/mossformer2_se/mossformer2.py
clearvoice-0.1.1.dist-info/METADATA
clearvoice-0.1.1.dist-info/WHEEL
clearvoice-0.1.1.dist-info/top_level.txt
clearvoice-0.1.1.dist-info/RECORD
