Metadata-Version: 2.4
Name: clearvoice
Version: 0.1.1
Summary: A unified inference platform for speech processing tasks
Author-email: Zhao Shengkui <shengkui.zhao@alibaba-inc.com>, Pan Zexu <zexu.pan@alibaba-inc.com>, Nguyen Trung Hieu <trunghieu.nguyen@alibaba-inc.com>
License-Expression: Apache-2.0
Project-URL: homepage, https://github.com/modelscope/ClearerVoice-Studio
Requires-Python: >=3.8
Requires-Dist: einops
Requires-Dist: gdown
Requires-Dist: huggingface-hub>=0.26.2
Requires-Dist: joblib
Requires-Dist: librosa==0.10.2.post1
Requires-Dist: numpy<2.0,>=1.24.3
Requires-Dist: opencv-python==4.10.0.84
Requires-Dist: packaging
Requires-Dist: pydub
Requires-Dist: python_speech_features==0.6
Requires-Dist: rotary_embedding_torch==0.8.3
Requires-Dist: scenedetect==0.6.6
Requires-Dist: scikit_learn
Requires-Dist: scipy>=1.10.1
Requires-Dist: soundfile==0.12.1
Requires-Dist: torch>=2.0.1
Requires-Dist: torchaudio>=2.0.2
Requires-Dist: torchinfo
Requires-Dist: torchvision
Requires-Dist: tqdm
Requires-Dist: yamlargparse
